LICENSE
MANIFEST.in
README.rst
setup.cfg
setup.py
sandsnake/__init__.py
sandsnake/exceptions.py
sandsnake/utils.py
sandsnake.egg-info/PKG-INFO
sandsnake.egg-info/SOURCES.txt
sandsnake.egg-info/dependency_links.txt
sandsnake.egg-info/requires.txt
sandsnake.egg-info/top_level.txt
sandsnake/backends/__init__.py
sandsnake/backends/base.py
sandsnake/backends/redis.py
tests/backends/__init__.py
tests/backends/redis_test.py