Metadata-Version: 1.0
Name: sandsnake
Version: 0.1.2
Summary: Sorted indexes backed by redis.
Home-page: https://github.com/numan/sandsnake
Author: Numan Sachwani
Author-email: numan856@gmail.com
License: Apache License 2.0
Platform: UNKNOWN
Classifier: Intended Audience :: Developers
Classifier: Intended Audience :: System Administrators
Classifier: Programming Language :: Python
Classifier: Topic :: Software Development
Classifier: Topic :: Utilities
